libname/__init__.py
libname/data_characteristics.py
icxpackage_data_characteristics-0.0.1.dist-info/LICENSE
icxpackage_data_characteristics-0.0.1.dist-info/METADATA
icxpackage_data_characteristics-0.0.1.dist-info/WHEEL
icxpackage_data_characteristics-0.0.1.dist-info/top_level.txt
icxpackage_data_characteristics-0.0.1.dist-info/RECORD
