Metadata-Version: 2.1
Name: icxpackage-data-characteristics
Version: 0.0.1
Summary: Package For Quick Data Overview For Analysis.
Home-page: UNKNOWN
Author: InfinityCodeX (Hardik Vegad)
Author-email: vegadhardik7@gmail.com
License: UNKNOWN
Keywords: python,numpy,pandas,data analysis,data science,data,seaborn,matplotlib
Platform: UNKNOWN
Classifier: Development Status :: 1 - Planning
Classifier: Intended Audience :: Developers
Classifier: Programming Language :: Python :: 3
Classifier: Operating System :: Unix
Classifier: Operating System :: MacOS :: MacOS X
Classifier: Operating System :: Microsoft :: Windows
License-File: LICENSE
Requires-Dist: numpy
Requires-Dist: pandas
Requires-Dist: matplotlib
Requires-Dist: seaborn
